[{
        "id": "1",
        "name": "厚磅寬版刺繡TEE(男女適穿)",
        "size": "M",
        "price": "NT$1,300",
        "img": "https://picsum.photos/id/237/250/300"
    },
    {
        "id": "2",
        "name": "厚磅寬版刺繡TEE(男女適穿)",
        "size": "M",
        "price": "NT$1,300",
        "img": "https://picsum.photos/id/237/250/300"
    },
    {
        "id": "3",
        "name": "厚磅寬版刺繡TEE(男女適穿)",
        "size": "M",
        "price": "NT$1,300",
        "img": "https://picsum.photos/id/237/250/300"
    },
    {
        "id": "4",
        "name": "厚磅寬版刺繡TEE(男女適穿)",
        "size": "M",
        "price": "NT$1,300",
        "img": "https://picsum.photos/id/237/250/300"
    },
    {
        "id": "5",
        "name": "厚磅寬版刺繡TEE(男女適穿)",
        "size": "M",
        "price": "NT$1,300",
        "img": "https://picsum.photos/id/237/250/300"
    },
    {
        "id": "6",
        "name": "厚磅寬版刺繡TEE(男女適穿)",
        "size": "M",
        "price": "NT$1,300",
        "img": "https://picsum.photos/id/237/250/300"
    },
    {
        "id": "7",
        "name": "厚磅寬版刺繡TEE(男女適穿)",
        "size": "M",
        "price": "NT$1,300",
        "img": "https://picsum.photos/id/237/250/300"
    },
    {
        "id": "8",
        "name": "厚磅寬版刺繡TEE(男女適穿)",
        "size": "M",
        "price": "NT$1,300",
        "img": "https://picsum.photos/id/237/250/300"
    }
]